django_zero_migrations_commands/__init__.py
django_zero_migrations_commands/settings.py
django_zero_migrations_commands/management/__init__.py
django_zero_migrations_commands/management/commands/__init__.py
django_zero_migrations_commands/management/commands/zeromigrations.py
django_zero_migrations_commands-1.0.3.dist-info/METADATA
django_zero_migrations_commands-1.0.3.dist-info/WHEEL
django_zero_migrations_commands-1.0.3.dist-info/licenses/LICENSE
django_zero_migrations_commands-1.0.3.dist-info/RECORD
