Metadata-Version: 2.4
Name: django-zero-migrations-commands
Version: 1.0.3
Summary: Management commands for creating and applying zero migrations.
Project-URL: Homepage, https://gitlab.com/software-design-public/django-zero-migrations-commands
Project-URL: Issues, https://gitlab.com/software-design-public/django-zero-migrations-commands/-/issues
Author-email: Julian Bürklin <jb@software-design.de>
License-File: LICENSE
Classifier: License :: OSI Approved :: MIT License
Classifier: Operating System :: OS Independent
Classifier: Programming Language :: Python :: 3
Requires-Python: >=3.6
